{
  "source": "https://r.jina.ai/http://www.imax.com/en/za/theatre/ster-kinekor-va-waterfront-imax",
  "theatre": "Ster-Kinekor V&A Waterfront IMAX",
  "items": [
    {
      "tmdb_id": 361743,
      "tmdb_url": "https://www.themoviedb.org/movie/361743",
      "tmdb_rating": "8.155",
      "tmdb_votes": "10864",
      "release_date": "2022-05-21",
      "overview": "After more than thirty years of service as one of the Navy’s top aviators, and dodging the advancement in rank that would ground him, Pete “Maverick” Mitchell finds himself training a detachment of TOP GUN graduates for a specialized mission the likes of which no living pilot has ever seen.",
      "runtime_minutes": "131",
      "genres": [
        "Action",
        "Drama"
      ],
      "directors": [
        "Joseph Kosinski"
      ],
      "actors": [
        "Tom Cruise",
        "Miles Teller",
        "Jennifer Connelly",
        "Bashir Salahuddin",
        "Jon Hamm",
        "Charles Parnell",
        "Monica Barbaro",
        "Lewis Pullman",
        "Jay Ellis",
        "Danny Ramirez"
      ],
      "trailer_url": "https://www.youtube.com/watch?v=Klc__shdj88",
      "poster_url": "https://image.tmdb.org/t/p/w342/n0YuM4f5lvGAP6MAW2kBIzugXnc.jpg",
      "title": "Top Gun: 40th Anniversary",
      "url": "http://www.imax.com/en/za/movie/top-gun-40th-anniversary",
      "source": "IMAX Waterfront",
      "status": "now_playing",
      "status_label": "Now playing",
      "showtimes": [
        "12:15",
        "17:45"
      ],
      "format": "IMAX 2D",
      "image": "https://image.tmdb.org/t/p/w342/n0YuM4f5lvGAP6MAW2kBIzugXnc.jpg"
    },
    {
      "tmdb_id": 361743,
      "tmdb_url": "https://www.themoviedb.org/movie/361743",
      "tmdb_rating": "8.155",
      "tmdb_votes": "10864",
      "release_date": "2022-05-21",
      "overview": "After more than thirty years of service as one of the Navy’s top aviators, and dodging the advancement in rank that would ground him, Pete “Maverick” Mitchell finds himself training a detachment of TOP GUN graduates for a specialized mission the likes of which no living pilot has ever seen.",
      "runtime_minutes": "131",
      "genres": [
        "Action",
        "Drama"
      ],
      "directors": [
        "Joseph Kosinski"
      ],
      "actors": [
        "Tom Cruise",
        "Miles Teller",
        "Jennifer Connelly",
        "Bashir Salahuddin",
        "Jon Hamm",
        "Charles Parnell",
        "Monica Barbaro",
        "Lewis Pullman",
        "Jay Ellis",
        "Danny Ramirez"
      ],
      "trailer_url": "https://www.youtube.com/watch?v=Klc__shdj88",
      "poster_url": "https://image.tmdb.org/t/p/w342/n0YuM4f5lvGAP6MAW2kBIzugXnc.jpg",
      "title": "Top Gun: Maverick",
      "url": "http://www.imax.com/en/za/movie/top-gun-maverick",
      "source": "IMAX Waterfront",
      "status": "coming_soon",
      "status_label": "Coming soon",
      "showtimes": [],
      "format": "",
      "image": "https://image.tmdb.org/t/p/w342/n0YuM4f5lvGAP6MAW2kBIzugXnc.jpg"
    },
    {
      "tmdb_id": 936075,
      "tmdb_url": "https://www.themoviedb.org/movie/936075",
      "tmdb_rating": "7.6",
      "tmdb_votes": "660",
      "release_date": "2026-04-22",
      "overview": "The story of Michael Jackson, one of the most influential artists the world has ever known, and his life beyond the music. His journey from the discovery of his extraordinary talent as the lead of the Jackson Five, to the visionary artist whose creative ambition fueled a relentless pursuit to become the biggest entertainer in the world, highlighting both his life off-stage and some of the most iconic performances from his early solo career.",
      "runtime_minutes": "128",
      "genres": [
        "Music",
        "Drama"
      ],
      "directors": [
        "Antoine Fuqua"
      ],
      "actors": [
        "Jaafar Jackson",
        "Colman Domingo",
        "Nia Long",
        "Juliano Krue Valdi",
        "Miles Teller",
        "KeiLyn Durrel Jones",
        "Kendrick Sampson",
        "Joseph David-Jones",
        "Rhyan Hill",
        "Jamal Henderson"
      ],
      "trailer_url": "https://www.youtube.com/watch?v=k-YAcjaLuSI",
      "poster_url": "https://image.tmdb.org/t/p/w342/3Qud19bBUrrJAzy0Ilm8gRJlJXP.jpg",
      "title": "Michael",
      "url": "http://www.imax.com/en/za/movie/michael",
      "source": "IMAX Waterfront",
      "status": "coming_soon",
      "status_label": "Coming soon",
      "showtimes": [],
      "format": "",
      "image": "https://image.tmdb.org/t/p/w342/3Qud19bBUrrJAzy0Ilm8gRJlJXP.jpg"
    },
    {
      "tmdb_id": 931285,
      "tmdb_url": "https://www.themoviedb.org/movie/931285",
      "tmdb_rating": "7.1",
      "tmdb_votes": "132",
      "release_date": "2026-05-06",
      "overview": "The fan favorite champions—now joined by Johnny Cage himself—are pitted against one another in the ultimate, no-holds barred, gory battle to defeat the dark rule of Shao Kahn that threatens the very existence of the Earthrealm and its defenders.",
      "runtime_minutes": "116",
      "genres": [
        "Action",
        "Fantasy",
        "Adventure"
      ],
      "directors": [
        "Simon McQuoid"
      ],
      "actors": [
        "Karl Urban",
        "Adeline Rudolph",
        "Jessica McNamee",
        "Ludi Lin",
        "Mehcad Brooks",
        "Josh Lawson",
        "Tati Gabrielle",
        "Lewis Tan",
        "Damon Herriman",
        "Chin Han"
      ],
      "trailer_url": "https://www.youtube.com/watch?v=zva2PQ-ud5Y",
      "poster_url": "https://image.tmdb.org/t/p/w342/lIsMeDbwntNXSUVHmWMMRXEZOVc.jpg",
      "title": "Mortal Kombat II",
      "url": "http://www.imax.com/en/za/movie/mortal-kombat-ii",
      "source": "IMAX Waterfront",
      "status": "coming_soon",
      "status_label": "Coming soon",
      "showtimes": [],
      "format": "",
      "image": "https://image.tmdb.org/t/p/w342/lIsMeDbwntNXSUVHmWMMRXEZOVc.jpg"
    },
    {
      "tmdb_id": 1228710,
      "tmdb_url": "https://www.themoviedb.org/movie/1228710",
      "tmdb_rating": "",
      "tmdb_votes": "",
      "release_date": "2026-05-20",
      "overview": "The evil Empire has fallen, and Imperial warlords remain scattered throughout the galaxy. As the fledgling New Republic works to protect everything the Rebellion fought for, they have enlisted the help of legendary Mandalorian bounty hunter Din Djarin and his young apprentice Grogu.",
      "runtime_minutes": "132",
      "genres": [
        "Adventure",
        "Science Fiction",
        "Action"
      ],
      "directors": [
        "Jon Favreau"
      ],
      "actors": [
        "Pedro Pascal",
        "Jeremy Allen White",
        "Sigourney Weaver",
        "Jonny Coyne",
        "Dave Filoni",
        "Steve Blum",
        "Martin Scorsese",
        "Hemky Madera",
        "Paul Sun-Hyung Lee",
        "Matthew Willig"
      ],
      "trailer_url": "https://www.youtube.com/watch?v=uwild1rw7Aw",
      "poster_url": "https://image.tmdb.org/t/p/w342/7QujwMB124KqSPbWlLRHBO5wygE.jpg",
      "title": "Star Wars: The Mandalorian and Grogu",
      "url": "http://www.imax.com/en/za/movie/the-mandalorian-and-grogu",
      "source": "IMAX Waterfront",
      "status": "coming_soon",
      "status_label": "Coming soon",
      "showtimes": [],
      "format": "",
      "image": "https://image.tmdb.org/t/p/w342/7QujwMB124KqSPbWlLRHBO5wygE.jpg"
    }
  ]
}